mdatapipe/__init__.py
mdatapipe/client/__init__.py
mdatapipe/client/__main__.py
mdatapipe/client/colorhelper.py
mdatapipe/client/commands.py
mdatapipe/client/testing.py
mdatapipe/core/__init__.py
mdatapipe/core/dynaconf.py
mdatapipe/core/engine.py
mdatapipe/core/pipeline.py
mdatapipe/core/select.py
mdatapipe/core/statistics.py
mdatapipe/core/utils.py
mdatapipe/engines/__init__.py
mdatapipe/engines/base/__init__.py
mdatapipe/engines/base/manager.py
mdatapipe/engines/base/plugin.py
mdatapipe/engines/multiprocessing/__init__.py
mdatapipe/engines/multiprocessing/manager.py
mdatapipe/engines/multiprocessing/plugin.py
mdatapipe/engines/singlethread/__init__.py
mdatapipe/engines/singlethread/manager.py
mdatapipe/engines/singlethread/plugin.py
mdatapipe/plugins/__init__.py
mdatapipe/plugins/base/__init__.py
mdatapipe/plugins/base/control/__init__.py
mdatapipe/plugins/collect/__init__.py
mdatapipe/plugins/collect/datasource/__init__.py
mdatapipe/plugins/collect/datasource/clock.py
mdatapipe/plugins/collect/datasource/command.py
mdatapipe/plugins/collect/datasource/file.py
mdatapipe/plugins/collect/datasource/file_delta.py
mdatapipe/plugins/collect/datasource/glob.py
mdatapipe/plugins/collect/datasource/http_server.py
mdatapipe/plugins/collect/datasource/influxdb.py
mdatapipe/plugins/collect/datasource/oracledb.py
mdatapipe/plugins/collect/datasource/url.py
mdatapipe/plugins/collect/inline/__init__.py
mdatapipe/plugins/collect/inline/list.py
mdatapipe/plugins/collect/inline/text.py
mdatapipe/plugins/collect/inline/yaml.py
mdatapipe/plugins/parse/__init__.py
mdatapipe/plugins/parse/line/__init__.py
mdatapipe/plugins/parse/line/csv.py
mdatapipe/plugins/parse/line/grok.py
mdatapipe/plugins/parse/line/ms_iis_log.py
mdatapipe/plugins/parse/line/nmon.py
mdatapipe/plugins/parse/line/regex.py
mdatapipe/plugins/parse/line/sar.py
mdatapipe/plugins/parse/line/xml_row.py
mdatapipe/plugins/parse/text/__init__.py
mdatapipe/plugins/parse/text/html_xpath.py
mdatapipe-0.0.3.dist-info/METADATA
mdatapipe-0.0.3.dist-info/WHEEL
mdatapipe-0.0.3.dist-info/entry_points.txt
mdatapipe-0.0.3.dist-info/top_level.txt
mdatapipe-0.0.3.dist-info/RECORD
