Metadata-Version: 2.1
Name: mdatapipe
Version: 0.0.3
Summary: Multiprocess plugin-driven engine for data collecting, analyzing and reporting
Home-page: https://github.com/mdatapipe/mdatapipe
Author: MDatapipe Team
Author-email: lamego.pinto@gmail.com
License: Apache-2
Platform: UNKNOWN
Classifier: Development Status :: 1 - Planning
Classifier: Environment :: Console
Classifier: Intended Audience :: Developers
Classifier: Intended Audience :: Information Technology
Classifier: Intended Audience :: System Administrators
Classifier: License :: Freely Distributable
Classifier: License :: OSI Approved :: Apache Software License
Classifier: Operating System :: OS Independent
Classifier: Programming Language :: Python
Classifier: Programming Language :: Python :: 3.6
Classifier: Topic :: Software Development :: Testing
Classifier: Topic :: Utilities
Requires-Dist: pip
Requires-Dist: pytz
Requires-Dist: pyyaml
Requires-Dist: click
Requires-Dist: requests
Requires-Dist: termcolor
Requires-Dist: colorama
